agent_ops_cockpit/__init__.py
agent_ops_cockpit/agent.py
agent_ops_cockpit/cost_control.py
agent_ops_cockpit/mcp_server.py
agent_ops_cockpit/optimizer.py
agent_ops_cockpit/system_prompt.md
agent_ops_cockpit/cache/__init__.py
agent_ops_cockpit/cache/semantic_cache.py
agent_ops_cockpit/cli/__init__.py
agent_ops_cockpit/cli/main.py
agent_ops_cockpit/eval/__init__.py
agent_ops_cockpit/eval/load_test.py
agent_ops_cockpit/eval/quality_climber.py
agent_ops_cockpit/eval/red_team.py
agent_ops_cockpit/ops/__init__.py
agent_ops_cockpit/ops/arch_review.py
agent_ops_cockpit/ops/cost_optimizer.py
agent_ops_cockpit/ops/evidence.py
agent_ops_cockpit/ops/evidence_bridge.py
agent_ops_cockpit/ops/frameworks.py
agent_ops_cockpit/ops/mcp_hub.py
agent_ops_cockpit/ops/memory_optimizer.py
agent_ops_cockpit/ops/orchestrator.py
agent_ops_cockpit/ops/pii_scrubber.py
agent_ops_cockpit/ops/policies.json
agent_ops_cockpit/ops/policy_engine.py
agent_ops_cockpit/ops/reliability.py
agent_ops_cockpit/ops/secret_scanner.py
agent_ops_cockpit/ops/swarm.py
agent_ops_cockpit/ops/ui_auditor.py
agent_ops_cockpit/ops/watcher.py
agent_ops_cockpit/ops/watchlist.json
agent_ops_cockpit/shadow/__init__.py
agent_ops_cockpit/shadow/router.py
agent_ops_cockpit/tests/golden_set.json
agent_ops_cockpit/tests/test_agent.py
agent_ops_cockpit/tests/test_arch_review.py
agent_ops_cockpit/tests/test_frameworks.py
agent_ops_cockpit/tests/test_optimizer.py
agent_ops_cockpit/tests/test_quality_climber.py
agent_ops_cockpit/tests/test_red_team.py
agent_ops_cockpit/tests/test_secret_scanner.py
agentops_cockpit-0.9.7.dist-info/METADATA
agentops_cockpit-0.9.7.dist-info/WHEEL
agentops_cockpit-0.9.7.dist-info/entry_points.txt
agentops_cockpit-0.9.7.dist-info/licenses/LICENSE
agentops_cockpit-0.9.7.dist-info/RECORD
