Metadata-Version: 2.4
Name: agentops-cockpit
Version: 0.9.7
Summary: Production-grade Agent Operations (AgentOps) Platform
Project-URL: Homepage, https://github.com/enriquekalven/agent-ops-cockpit
Project-URL: Bug Tracker, https://github.com/enriquekalven/agent-ops-cockpit/issues
Author-email: Enrique <enrique@example.com>
License-File: LICENSE
Classifier: License :: OSI Approved :: MIT License
Classifier: Operating System :: OS Independent
Classifier: Programming Language :: Python :: 3
Requires-Python: >=3.10
Requires-Dist: aiohttp>=3.9.0
Requires-Dist: fastapi>=0.100.0
Requires-Dist: gitpython>=3.1.0
Requires-Dist: mcp>=0.1.0
Requires-Dist: packaging>=23.0
Requires-Dist: pydantic>=2.0.0
Requires-Dist: rich>=13.0.0
Requires-Dist: tenacity>=8.0.0
Requires-Dist: typer>=0.9.0
Requires-Dist: uvicorn>=0.20.0
